efemarai/__init__.py
efemarai/base_checker.py
efemarai/baseline.py
efemarai/cli.py
efemarai/console.py
efemarai/dataset.py
efemarai/definition_checker.py
efemarai/domain.py
efemarai/hooks.py
efemarai/job_state.py
efemarai/model.py
efemarai/problem_type.py
efemarai/project.py
efemarai/reports.py
efemarai/runtime_checker.py
efemarai/session.py
efemarai/spec.py
efemarai/stress_test.py
efemarai/domains/__init__.py
efemarai/domains/color.yaml
efemarai/domains/geometric.yaml
efemarai/domains/noise.yaml
efemarai/domains/text.yaml
efemarai/fields/__init__.py
efemarai/fields/annotation_fields.py
efemarai/fields/base_fields.py
efemarai/fields/data_fields.py
efemarai/fields/datapoint.py
efemarai/formats/__init__.py
efemarai/formats/config.py
efemarai/formats/dataset_coco.py
efemarai/formats/dataset_imagenet.py
efemarai/metamorph/__init__.py
efemarai/metamorph/adaptors.py
efemarai/metamorph/base_metamorphs.py
efemarai/metamorph/domain.py
efemarai/metamorph/domain_loader.py
efemarai/metamorph/operators_registry.py
efemarai/metamorph/search_domain.py
efemarai/metamorph/loss/__init__.py
efemarai/metamorph/loss/bounding_box_loss.py
efemarai/metamorph/loss/classification_loss.py
efemarai/metamorph/loss/datapoint_loss.py
efemarai/metamorph/loss/instance_segmentation_loss.py
efemarai/metamorph/loss/keypoint_loss.py
efemarai/metamorph/loss/loss_functions.py
efemarai/metamorph/loss/matching.py
efemarai/metamorph/loss/regression_loss.py
efemarai/metamorph/loss/text_loss.py
efemarai/metamorph/text/__init__.py
efemarai/metamorph/text/text_metamorphs.py
efemarai/metamorph/vision/__init__.py
efemarai/metamorph/vision/vision_metamorphs.py
efemarai/metamorph/vision/operators/__init__.py
efemarai/metamorph/vision/operators/custom_operators.py
efemarai-0.4.2.dist-info/METADATA
efemarai-0.4.2.dist-info/WHEEL
efemarai-0.4.2.dist-info/entry_points.txt
efemarai-0.4.2.dist-info/top_level.txt
efemarai-0.4.2.dist-info/RECORD
