Metadata-Version: 2.1
Name: efemarai
Version: 0.4.2
Summary: A CLI and SDK for interacting with the Efemarai ML testing platform.
Home-page: https://www.efemarai.com/
Author: Efemarai
Author-email: support@efemarai.com
License: MIT license
Requires-Python: >=3.6
Requires-Dist: pyaml (>=21.10.1)
Requires-Dist: requests (>=2.25.1)
Requires-Dist: smart-open (>=5.2.1)
Requires-Dist: boto3 (>=1.20.39)
Requires-Dist: appdirs (>=1.4.4)
Requires-Dist: rich (>=11.0.0)
Requires-Dist: validators (>=0.18.2)
Requires-Dist: urllib3 (>=1.25.4)
Requires-Dist: click (>=8.0.4)
Requires-Dist: click-completion (>=0.5.2)
Requires-Dist: click-aliases (>=1.0.1)
Requires-Dist: GitPython (>=3.1.20)
Requires-Dist: furl (>=2.1.3)
Requires-Dist: numpy (>=1.18.4)
Requires-Dist: Pillow (>=8.4)
Requires-Dist: pathspec (>=0.9.0)
Requires-Dist: python-slugify (>=6.1.2)
Requires-Dist: bson (>=0.5.10)
Requires-Dist: ffmpeg-python (>=0.2.0)
Requires-Dist: opencv-python-headless (>=3.4.15.55)
Provides-Extra: full
Requires-Dist: hyperactive (>=4.4.3) ; extra == 'full'
Requires-Dist: albumentations (>=1.3.0) ; extra == 'full'
Requires-Dist: pandas (>=1.2.0) ; extra == 'full'
Requires-Dist: nltk (>=3.8.1) ; extra == 'full'
Requires-Dist: nlpaug (>=1.1.11) ; extra == 'full'
Requires-Dist: gensim (>=4.0.1) ; extra == 'full'
Requires-Dist: sacremoses (>=0.0.53) ; extra == 'full'
Requires-Dist: transformers (>=4.16.2) ; extra == 'full'
Requires-Dist: torchmetrics (>=0.11.4) ; extra == 'full'
